langchain_permit/__init__.py
langchain_permit/examples/config/jwks.json
langchain_permit/examples/demo_scripts/demo_ensemble.py
langchain_permit/examples/demo_scripts/demo_jwt_validation.py
langchain_permit/examples/demo_scripts/demo_permissions_check.py
langchain_permit/examples/demo_scripts/demo_self_query.py
langchain_permit/examples/demo_scripts/test_get_claims.py
langchain_permit/examples/demo_scripts/test_jwt_fetching.py
langchain_permit/examples/demo_scripts/test_validate.py
langchain_permit/examples/demo_scripts/test_validator_tools.py
langchain_permit/py.typed
langchain_permit/retrievers.py
langchain_permit/tools.py
langchain_permit/validator.py
langchain_permit-0.1.4.dist-info/LICENSE
langchain_permit-0.1.4.dist-info/METADATA
langchain_permit-0.1.4.dist-info/WHEEL
langchain_permit-0.1.4.dist-info/RECORD
