Metadata-Version: 2.3
Name: langchain-permit
Version: 0.1.4
Summary: Access control tools and retrievers for LangChain.
License: MIT
Requires-Python: >=3.9,<4.0
Classifier: License :: OSI Approved :: MIT License
Classifier: Programming Language :: Python :: 3
Classifier: Programming Language :: Python :: 3.9
Classifier: Programming Language :: Python :: 3.10
Classifier: Programming Language :: Python :: 3.11
Classifier: Programming Language :: Python :: 3.12
Classifier: Programming Language :: Python :: 3.13
Requires-Dist: chromadb (>=0.6.3,<0.7.0)
Requires-Dist: jwcrypto (>=1.5.6,<2.0.0)
Requires-Dist: langchain (>=0.3.18,<0.4.0)
Requires-Dist: langchain-chroma (>=0.2.2,<0.3.0)
Requires-Dist: langchain-community (>=0.3.17,<0.4.0)
Requires-Dist: langchain-core (>=0.3.15,<0.4.0)
Requires-Dist: langchain-openai (>=0.3.5,<0.4.0)
Requires-Dist: langchain-tests (>=0.3.11,<0.4.0)
Requires-Dist: libmagic (>=1.0,<2.0)
Requires-Dist: openai (>=1.63.0,<2.0.0)
Requires-Dist: permit (>=2.7.1,<3.0.0)
Requires-Dist: pydantic (>=2.10.6,<3.0.0)
Requires-Dist: pyjwt (>=2.10.1,<3.0.0)
Requires-Dist: python-dotenv (>=1.0.1,<2.0.0)
Requires-Dist: tiktoken (>=0.9.0,<0.10.0)
Requires-Dist: unstructured (>=0.16.20,<0.17.0)
Project-URL: Repository, https://github.com/permitio/langchain-permit
Project-URL: Release Notes, https://github.com/langchain-ai/langchain/releases?q=tag%3A%22permit%3D%3D0%22&expanded=true
Project-URL: Source Code, https://github.com/langchain-ai/langchain/tree/master/libs/partners/permit
